djangorest_security/__init__.py
djangorest_security/authenticators/__init__.py
djangorest_security/authenticators/shared_key.py
djangorest_security/decorators/__init__.py
djangorest_security/decorators/authorize.py
djangorest_security-0.0.3.dist-info/LICENSE
djangorest_security-0.0.3.dist-info/METADATA
djangorest_security-0.0.3.dist-info/WHEEL
djangorest_security-0.0.3.dist-info/top_level.txt
djangorest_security-0.0.3.dist-info/RECORD
